fewsats_mcp/__init__.py
fewsats_mcp/__main__.py
fewsats_mcp/server.py
iflow_mcp_fewsats_mcp-0.1.6.dist-info/METADATA
iflow_mcp_fewsats_mcp-0.1.6.dist-info/WHEEL
iflow_mcp_fewsats_mcp-0.1.6.dist-info/entry_points.txt
iflow_mcp_fewsats_mcp-0.1.6.dist-info/RECORD
