Metadata-Version: 2.4
Name: iflow-mcp_fewsats-mcp
Version: 0.1.6
Summary: Fewsats MCP server
Requires-Python: >=3.10
Requires-Dist: fewsats>=0.0.22
Requires-Dist: mcp>=1.4.1
